CHANGES
Makefile
__init__.py
ez_setup.py
setup.cfg
setup.py
pyMessaging.egg-info/SOURCES.txt
pymessaging/__init__.py
pymessaging/zwitschr.py