Metadata-Version: 1.0
Name: pyMessaging
Version: 0.3-r4247
Summary: Message Passing Framework for Python.
Home-page: http://cybernetics.hudora.biz/dist/pyMessaging/
Author: Maximillian Dornseif
Author-email: md@hudora.de
License: BSD
Platform: UNKNOWN
Classifier: Intended Audience :: Developers
Classifier: Programming Language :: Python
